ma/__init__.py
ma/ma_plot.py
matplot_for_finance-0.0.3.dist-info/METADATA
matplot_for_finance-0.0.3.dist-info/WHEEL
matplot_for_finance-0.0.3.dist-info/top_level.txt
matplot_for_finance-0.0.3.dist-info/RECORD
